tonpy-0.0.0.1.4rc0.data/purelib/tonpy/__init__.py
tonpy-0.0.0.1.4rc0.data/purelib/tonpy/scheduler.py
tonpy-0.0.0.1.4rc0.data/purelib/tonpy/abi/__init__.py
tonpy-0.0.0.1.4rc0.data/purelib/tonpy/abi/getter.py
tonpy-0.0.0.1.4rc0.data/purelib/tonpy/abi/getter_cache.py
tonpy-0.0.0.1.4rc0.data/purelib/tonpy/abi/instance.py
tonpy-0.0.0.1.4rc0.data/purelib/tonpy/abi/interface.py
tonpy-0.0.0.1.4rc0.data/purelib/tonpy/autogen/__init__.py
tonpy-0.0.0.1.4rc0.data/purelib/tonpy/autogen/block.py
tonpy-0.0.0.1.4rc0.data/purelib/tonpy/blockscanner/__init__.py
tonpy-0.0.0.1.4rc0.data/purelib/tonpy/blockscanner/blockscanner.py
tonpy-0.0.0.1.4rc0.data/purelib/tonpy/blockscanner/database_provider.py
tonpy-0.0.0.1.4rc0.data/purelib/tonpy/blockscanner/subscriptions.py
tonpy-0.0.0.1.4rc0.data/purelib/tonpy/blockscanner/txs_inblock_emulator.py
tonpy-0.0.0.1.4rc0.data/purelib/tonpy/data_for_tests/__init__.py
tonpy-0.0.0.1.4rc0.data/purelib/tonpy/data_for_tests/block_boc.py
tonpy-0.0.0.1.4rc0.data/purelib/tonpy/data_for_tests/dict_test_boc.py
tonpy-0.0.0.1.4rc0.data/purelib/tonpy/data_for_tests/emulator_data.py
tonpy-0.0.0.1.4rc0.data/purelib/tonpy/data_for_tests/raw_emulator_data_for_test.py
tonpy-0.0.0.1.4rc0.data/purelib/tonpy/fift/__init__.py
tonpy-0.0.0.1.4rc0.data/purelib/tonpy/fift/disasm.py
tonpy-0.0.0.1.4rc0.data/purelib/tonpy/fift/fift.py
tonpy-0.0.0.1.4rc0.data/purelib/tonpy/fift/libs/Asm.fif
tonpy-0.0.0.1.4rc0.data/purelib/tonpy/fift/libs/Color.fif
tonpy-0.0.0.1.4rc0.data/purelib/tonpy/fift/libs/Disasm.fif
tonpy-0.0.0.1.4rc0.data/purelib/tonpy/fift/libs/Fift.fif
tonpy-0.0.0.1.4rc0.data/purelib/tonpy/fift/libs/FiftExt.fif
tonpy-0.0.0.1.4rc0.data/purelib/tonpy/fift/libs/GetOpt.fif
tonpy-0.0.0.1.4rc0.data/purelib/tonpy/fift/libs/Lisp.fif
tonpy-0.0.0.1.4rc0.data/purelib/tonpy/fift/libs/Lists.fif
tonpy-0.0.0.1.4rc0.data/purelib/tonpy/fift/libs/Stack.fif
tonpy-0.0.0.1.4rc0.data/purelib/tonpy/fift/libs/TonUtil.fif
tonpy-0.0.0.1.4rc0.dist-info/LICENSE
tonpy-0.0.0.1.4rc0.dist-info/METADATA
tonpy-0.0.0.1.4rc0.dist-info/WHEEL
tonpy-0.0.0.1.4rc0.dist-info/top_level.txt
tonpy-0.0.0.1.4rc0.dist-info/RECORD
