Metadata-Version: 2.1
Name: tonpy
Version: 0.0.0.1.4rc0
Summary: Types / API for TON blockchain
Home-page: https://github.com/disintar/tonpy
Author: Disintar LLP
Author-email: andrey@head-labs.com
Project-URL: Bug Tracker, https://github.com/disintar/tonpy/issues
Classifier: License :: OSI Approved :: Apache Software License
Classifier: Operating System :: OS Independent
Classifier: Intended Audience :: Developers
Classifier: Programming Language :: Python :: 3
Classifier: Programming Language :: Python :: Implementation :: PyPy
Requires-Python: >=3.8,<3.14
License-File: LICENSE
Requires-Dist: loguru
Requires-Dist: pytest
Requires-Dist: bitstring
Requires-Dist: orjson
Requires-Dist: tqdm
Requires-Dist: requests
Requires-Dist: cytoolz
Requires-Dist: asgiref
Requires-Dist: pytest-asyncio
Provides-Extra: built
Requires-Dist: setuptools==68.0.0; extra == "built"
Requires-Dist: build==1.2.1; extra == "built"
Requires-Dist: twine; extra == "built"
Provides-Extra: docs
Requires-Dist: Sphinx>=3.0.0; extra == "docs"
Requires-Dist: docutils; extra == "docs"
Requires-Dist: pylons-sphinx-themes>=1.0.8; extra == "docs"
Requires-Dist: pylons-sphinx-latesturl; extra == "docs"
Requires-Dist: repoze.sphinx.autointerface; extra == "docs"
Requires-Dist: sphinxcontrib-autoprogram; extra == "docs"
Requires-Dist: sphinx-rtd-theme; extra == "docs"
